easyllm/__init__.py
easyllm/cli.py
easyllm/clients/__init__.py
easyllm/clients/bedrock.py
easyllm/clients/huggingface.py
easyllm/clients/sagemaker.py
easyllm/evol_instruct/__init__.py
easyllm/prompt_utils/__init__.py
easyllm/prompt_utils/anthropic.py
easyllm/prompt_utils/base.py
easyllm/prompt_utils/chatml_hf.py
easyllm/prompt_utils/falcon.py
easyllm/prompt_utils/llama2.py
easyllm/prompt_utils/open_assistant.py
easyllm/prompt_utils/stablebeluga.py
easyllm/prompt_utils/vicuna.py
easyllm/prompt_utils/wizardlm.py
easyllm/schema/base.py
easyllm/schema/openai.py
easyllm/utils/__init__.py
easyllm/utils/aws.py
easyllm/utils/logging.py
easyllm-0.6.2.dist-info/METADATA
easyllm-0.6.2.dist-info/WHEEL
easyllm-0.6.2.dist-info/entry_points.txt
easyllm-0.6.2.dist-info/licenses/LICENSE
easyllm-0.6.2.dist-info/RECORD
