Metadata-Version: 2.1
Name: easyllm
Version: 0.6.2
Summary: Description
Project-URL: Documentation, https://github.com/unknown/hatch-demo#readme
Project-URL: Issues, https://github.com/unknown/hatch-demo/issues
Project-URL: Source, https://github.com/unknown/hatch-demo
Author-email: Philipp Schmid <schmidphilipp1995@gmail.com>
License-Expression: MIT
License-File: LICENSE
Classifier: Intended Audience :: Developers
Classifier: License :: OSI Approved :: MIT License
Classifier: Programming Language :: Python :: 3 :: Only
Classifier: Programming Language :: Python :: 3.8
Classifier: Programming Language :: Python :: 3.9
Classifier: Programming Language :: Python :: 3.10
Classifier: Topic :: Internet
Classifier: Topic :: Software Development
Classifier: Topic :: Software Development :: Libraries
Classifier: Topic :: Software Development :: Libraries :: Application Frameworks
Classifier: Topic :: Software Development :: Libraries :: Python Modules
Requires-Python: >=3.8
Requires-Dist: huggingface-hub==0.16.4
Requires-Dist: nanoid==2.0.0
Requires-Dist: pydantic==2.1.1
Provides-Extra: bedrock
Requires-Dist: boto3; extra == 'bedrock'
Provides-Extra: dev
Requires-Dist: black; extra == 'dev'
Requires-Dist: hatch; extra == 'dev'
Requires-Dist: isort; extra == 'dev'
Requires-Dist: mypy; extra == 'dev'
Requires-Dist: ruff; extra == 'dev'
Provides-Extra: docs
Requires-Dist: mkdocs; extra == 'docs'
Requires-Dist: mkdocs-autorefs; extra == 'docs'
Requires-Dist: mkdocs-jupyter; extra == 'docs'
Requires-Dist: mkdocs-material; extra == 'docs'
Requires-Dist: mkdocstrings; extra == 'docs'
Requires-Dist: mkdocstrings-python; extra == 'docs'
Provides-Extra: test
Requires-Dist: black; extra == 'test'
Requires-Dist: hatch; extra == 'test'
Requires-Dist: isort; extra == 'test'
Requires-Dist: mypy; extra == 'test'
Requires-Dist: pytest; extra == 'test'
Requires-Dist: ruff; extra == 'test'
